game/__init__.py
game/api.py
game/gameplay.py
game/main.py
game/main_menu.py
game/memory.py
game/narrative.py
game/settings.py
game/ui.py
veritaminal-1.0.3.dist-info/licenses/LICENSE
veritaminal-1.0.3.dist-info/METADATA
veritaminal-1.0.3.dist-info/WHEEL
veritaminal-1.0.3.dist-info/entry_points.txt
veritaminal-1.0.3.dist-info/top_level.txt
veritaminal-1.0.3.dist-info/RECORD
