Metadata-Version: 2.4
Name: veritaminal
Version: 1.0.3
Summary: A terminal-based document verification game
Home-page: https://github.com/maverickkamal/veritaminal
Author: Maverick
Author-email: kamaludeenmoussa@gmail.com
Classifier: Programming Language :: Python :: 3
Classifier: License :: OSI Approved :: MIT License
Classifier: Operating System :: OS Independent
Classifier: Environment :: Console
Classifier: Topic :: Games/Entertainment
Classifier: Intended Audience :: End Users/Desktop
Requires-Python: >=3.8
License-File: LICENSE
Requires-Dist: google-genai>=1.5.0
Requires-Dist: prompt_toolkit>=3.0.50
Requires-Dist: python-dotenv>=1.0.1
Requires-Dist: requests>=2.32.1
Requires-Dist: colorama>=0.4.6
Requires-Dist: pydantic>=2.10.6
Dynamic: author
Dynamic: author-email
Dynamic: classifier
Dynamic: description
Dynamic: description-content-type
Dynamic: home-page
Dynamic: license-file
Dynamic: requires-dist
Dynamic: requires-python
Dynamic: summary
